pyslobs/__init__.py
pyslobs/api.py
pyslobs/apibase.py
pyslobs/config.py
pyslobs/connection.py
pyslobs/pubsubhub.py
pyslobs/slobs/__init__.py
pyslobs/slobs/audioservice.py
pyslobs/slobs/audiosource.py
pyslobs/slobs/factories.py
pyslobs/slobs/notificationsservice.py
pyslobs/slobs/performanceservice.py
pyslobs/slobs/scene.py
pyslobs/slobs/scenecollectionservice.py
pyslobs/slobs/scenenode.py
pyslobs/slobs/scenesservice.py
pyslobs/slobs/selection.py
pyslobs/slobs/selectionbase.py
pyslobs/slobs/selectionservice.py
pyslobs/slobs/source.py
pyslobs/slobs/sourcesservice.py
pyslobs/slobs/streamingservice.py
pyslobs/slobs/transitionsservice.py
pyslobs/slobs/typedefs.py
pyslobs-2.1.0.dist-info/licenses/LICENSE
pyslobs-2.1.0.dist-info/METADATA
pyslobs-2.1.0.dist-info/WHEEL
pyslobs-2.1.0.dist-info/top_level.txt
pyslobs-2.1.0.dist-info/RECORD
