Metadata-Version: 2.4
Name: PySLOBS
Version: 2.1.0
Summary: Python wrapper to StreamLabs Desktop API
Home-page: https://github.com/Julian-O/pyslobs
Author: Julian-O
Classifier: Programming Language :: Python :: 3
Classifier: Operating System :: OS Independent
Classifier: Development Status :: 5 - Production/Stable
Classifier: Framework :: AsyncIO
Classifier: Intended Audience :: Developers
Classifier: Topic :: Multimedia :: Video
Requires-Python: >=3.10
License-File: LICENSE
Requires-Dist: websocket-client
Dynamic: author
Dynamic: classifier
Dynamic: description
Dynamic: description-content-type
Dynamic: home-page
Dynamic: license-file
Dynamic: requires-dist
Dynamic: requires-python
Dynamic: summary
